k8s_scheduler/LogHandler.py
k8s_scheduler/ResultsBackend.py
k8s_scheduler/SchedulerBackend.py
k8s_scheduler/__init__.py
k8s_scheduler/connection.py
k8s_scheduler/scheduler.py
k8s_scheduler-0.0.13.dist-info/LICENSE
k8s_scheduler-0.0.13.dist-info/METADATA
k8s_scheduler-0.0.13.dist-info/WHEEL
k8s_scheduler-0.0.13.dist-info/top_level.txt
k8s_scheduler-0.0.13.dist-info/RECORD
