Metadata-Version: 2.1
Name: k8s-scheduler
Version: 0.0.13
Summary: Basic Scheduler for k8s
Home-page: https://github.com/saikiran2603/k8s-scheduler/
Author: Sai Kiran
Author-email: neo2603@gmail.com
License: UNKNOWN
Project-URL: Bug Tracker, https://github.com/saikiran2603/k8s-scheduler/issues
Project-URL: homepage, https://github.com/saikiran2603/k8s-scheduler/
Project-URL: documentation, https://github.com/saikiran2603/k8s-scheduler/blob/master/README.md
Project-URL: source, https://github.com/saikiran2603/k8s-scheduler/
Project-URL: download, https://github.com/saikiran2603/k8s-scheduler/releases
Project-URL: tracker, https://github.com/saikiran2603/k8s-scheduler/issues
Platform: UNKNOWN
Classifier: Development Status :: 5 - Production/Stable
Classifier: Intended Audience :: Science/Research
Classifier: Intended Audience :: Developers
Classifier: License :: OSI Approved :: BSD License
Classifier: Programming Language :: C
Classifier: Programming Language :: Python
Classifier: Programming Language :: Python :: 3
Classifier: Programming Language :: Python :: 3.8
Classifier: Programming Language :: Python :: 3.9
Classifier: Programming Language :: Python :: 3.10
Classifier: Topic :: Software Development :: Libraries
Classifier: Topic :: Scientific/Engineering
Classifier: Operating System :: Microsoft :: Windows
Classifier: Operating System :: POSIX :: Linux
Classifier: Operating System :: POSIX
Classifier: Operating System :: Unix
Classifier: Operating System :: MacOS
Requires-Python: >=3.6
License-File: LICENSE
Requires-Dist: setuptools (>=42)
Requires-Dist: pymongo (>=4.0.2)
Requires-Dist: croniter (>=1.3.4)
Requires-Dist: kubernetes (>=23.3.0)
Requires-Dist: python-dateutil (>=2.8.2)
